sahara_plugin_vanilla/__init__.py
sahara_plugin_vanilla/i18n.py
sahara_plugin_vanilla/locale/de/LC_MESSAGES/sahara_plugin_vanilla.po
sahara_plugin_vanilla/locale/en_GB/LC_MESSAGES/sahara_plugin_vanilla.po
sahara_plugin_vanilla/locale/id/LC_MESSAGES/sahara_plugin_vanilla.po
sahara_plugin_vanilla/locale/ne/LC_MESSAGES/sahara_plugin_vanilla.po
sahara_plugin_vanilla/plugins/__init__.py
sahara_plugin_vanilla/plugins/vanilla/__init__.py
sahara_plugin_vanilla/plugins/vanilla/abstractversionhandler.py
sahara_plugin_vanilla/plugins/vanilla/confighints_helper.py
sahara_plugin_vanilla/plugins/vanilla/edp_engine.py
sahara_plugin_vanilla/plugins/vanilla/plugin.py
sahara_plugin_vanilla/plugins/vanilla/utils.py
sahara_plugin_vanilla/plugins/vanilla/versionfactory.py
sahara_plugin_vanilla/plugins/vanilla/hadoop2/__init__.py
sahara_plugin_vanilla/plugins/vanilla/hadoop2/config.py
sahara_plugin_vanilla/plugins/vanilla/hadoop2/config_helper.py
sahara_plugin_vanilla/plugins/vanilla/hadoop2/edp_engine.py
sahara_plugin_vanilla/plugins/vanilla/hadoop2/keypairs.py
sahara_plugin_vanilla/plugins/vanilla/hadoop2/oozie_helper.py
sahara_plugin_vanilla/plugins/vanilla/hadoop2/recommendations_utils.py
sahara_plugin_vanilla/plugins/vanilla/hadoop2/run_scripts.py
sahara_plugin_vanilla/plugins/vanilla/hadoop2/scaling.py
sahara_plugin_vanilla/plugins/vanilla/hadoop2/starting_scripts.py
sahara_plugin_vanilla/plugins/vanilla/hadoop2/utils.py
sahara_plugin_vanilla/plugins/vanilla/hadoop2/validation.py
sahara_plugin_vanilla/plugins/vanilla/hadoop2/resources/create_oozie_db.sql
sahara_plugin_vanilla/plugins/vanilla/hadoop2/resources/post_conf.template
sahara_plugin_vanilla/plugins/vanilla/hadoop2/resources/spark-cleanup.cron
sahara_plugin_vanilla/plugins/vanilla/hadoop2/resources/tmp-cleanup.sh.template
sahara_plugin_vanilla/plugins/vanilla/hadoop2/resources/topology.sh
sahara_plugin_vanilla/plugins/vanilla/hadoop2/resources/zoo_sample.cfg
sahara_plugin_vanilla/plugins/vanilla/v2_7_1/__init__.py
sahara_plugin_vanilla-10.0.0.dist-info/AUTHORS
sahara_plugin_vanilla-10.0.0.dist-info/LICENSE
sahara_plugin_vanilla-10.0.0.dist-info/METADATA
sahara_plugin_vanilla-10.0.0.dist-info/WHEEL
sahara_plugin_vanilla-10.0.0.dist-info/entry_points.txt
sahara_plugin_vanilla-10.0.0.dist-info/pbr.json
sahara_plugin_vanilla-10.0.0.dist-info/top_level.txt
sahara_plugin_vanilla-10.0.0.dist-info/RECORD
